Metadata-Version: 2.1
Name: argo-workflows-fvdnabee
Version: 3.6.1
Summary: Client for Argo Workflows
Home-page: https://github.com/CermakM/argo-client-python
Author: Marek Cermak
Author-email: macermak@redhat.com
License: MIT
Platform: UNKNOWN
Classifier: Development Status :: 3 - Alpha
Classifier: Intended Audience :: Developers
Classifier: Intended Audience :: Information Technology
Classifier: License :: OSI Approved :: MIT License
Classifier: Operating System :: OS Independent
Classifier: Programming Language :: Python :: 3.6
Classifier: Programming Language :: Python :: 3.7
Classifier: Topic :: Software Development
Classifier: Topic :: Utilities
Requires-Dist: kubernetes (==12.0.0a1)
Requires-Dist: mock
